{
  "hub": {
    "node_id": "N001",
    "name": "Veridian City Central Hub",
    "location": "Central District - Zone A",
    "last_updated": "2024-01-15T08:00:00"
  },
  "inventory": [
    {
      "resource_id": "R001",
      "name": "Food Packets",
      "category": "food",
      "total_stock": 5000,
      "unit": "packets",
      "distributed": 0,
      "in_transit": 0
    },
    {
      "resource_id": "R002",
      "name": "Water",
      "category": "water",
      "total_stock": 8000,
      "unit": "liters",
      "distributed": 0,
      "in_transit": 0
    },
    {
      "resource_id": "R003",
      "name": "Medical Kits",
      "category": "medical",
      "total_stock": 500,
      "unit": "kits",
      "distributed": 0,
      "in_transit": 0
    },
    {
      "resource_id": "R004",
      "name": "Blankets",
      "category": "shelter",
      "total_stock": 2000,
      "unit": "pieces",
      "distributed": 0,
      "in_transit": 0
    },
    {
      "resource_id": "R005",
      "name": "Rescue Boats",
      "category": "equipment",
      "total_stock": 20,
      "unit": "units",
      "distributed": 0,
      "in_transit": 0
    },
    {
      "resource_id": "R006",
      "name": "Emergency Medicines",
      "category": "medical",
      "total_stock": 300,
      "unit": "kits",
      "distributed": 0,
      "in_transit": 0
    }
  ],
  "safe_zone_allocations": [],
  "distribution_log": []
}
